TwinCons-0.6.2.dev0.data/data/matrices/LG.dat
TwinCons-0.6.2.dev0.data/data/matrices/BLOSUM/blosum100.out
TwinCons-0.6.2.dev0.data/data/matrices/BLOSUM/blosum30.out
TwinCons-0.6.2.dev0.data/data/matrices/BLOSUM/blosum35.out
TwinCons-0.6.2.dev0.data/data/matrices/BLOSUM/blosum40.out
TwinCons-0.6.2.dev0.data/data/matrices/BLOSUM/blosum45.out
TwinCons-0.6.2.dev0.data/data/matrices/BLOSUM/blosum50.out
TwinCons-0.6.2.dev0.data/data/matrices/BLOSUM/blosum55.out
TwinCons-0.6.2.dev0.data/data/matrices/BLOSUM/blosum60.out
TwinCons-0.6.2.dev0.data/data/matrices/BLOSUM/blosum62.out
TwinCons-0.6.2.dev0.data/data/matrices/BLOSUM/blosum65.out
TwinCons-0.6.2.dev0.data/data/matrices/BLOSUM/blosum70.out
TwinCons-0.6.2.dev0.data/data/matrices/BLOSUM/blosum75.out
TwinCons-0.6.2.dev0.data/data/matrices/BLOSUM/blosum80.out
TwinCons-0.6.2.dev0.data/data/matrices/BLOSUM/blosum85.out
TwinCons-0.6.2.dev0.data/data/matrices/BLOSUM/blosum90.out
TwinCons-0.6.2.dev0.data/data/matrices/BLOSUM/blosum95.out
TwinCons-0.6.2.dev0.data/data/matrices/jp/BO.dat
TwinCons-0.6.2.dev0.data/data/matrices/jp/benner22.dat
TwinCons-0.6.2.dev0.data/data/matrices/jp/benner74.dat
TwinCons-0.6.2.dev0.data/data/matrices/jp/blastn.dat
TwinCons-0.6.2.dev0.data/data/matrices/jp/blosum100.dat
TwinCons-0.6.2.dev0.data/data/matrices/jp/blosum30.dat
TwinCons-0.6.2.dev0.data/data/matrices/jp/blosum35.dat
TwinCons-0.6.2.dev0.data/data/matrices/jp/blosum40.dat
TwinCons-0.6.2.dev0.data/data/matrices/jp/blosum45.dat
TwinCons-0.6.2.dev0.data/data/matrices/jp/blosum50.dat
TwinCons-0.6.2.dev0.data/data/matrices/jp/blosum55.dat
TwinCons-0.6.2.dev0.data/data/matrices/jp/blosum60.dat
TwinCons-0.6.2.dev0.data/data/matrices/jp/blosum62.dat
TwinCons-0.6.2.dev0.data/data/matrices/jp/blosum65.dat
TwinCons-0.6.2.dev0.data/data/matrices/jp/blosum70.dat
TwinCons-0.6.2.dev0.data/data/matrices/jp/blosum75.dat
TwinCons-0.6.2.dev0.data/data/matrices/jp/blosum80.dat
TwinCons-0.6.2.dev0.data/data/matrices/jp/blosum85.dat
TwinCons-0.6.2.dev0.dist-info/LICENSE
TwinCons-0.6.2.dev0.dist-info/METADATA
TwinCons-0.6.2.dev0.dist-info/WHEEL
TwinCons-0.6.2.dev0.dist-info/top_level.txt
TwinCons-0.6.2.dev0.dist-info/RECORD
