Metadata-Version: 2.1
Name: TwinCons
Version: 0.6.2.dev0
Summary: This projects provides several packages for analysis of MSAs comprised of two sequence groups.
Home-page: https://github.com/petaripenev/AlignmentScore
Author: Petar Penev
Author-email: ppenev@gatech.edu
License: UNKNOWN
Platform: UNKNOWN
Classifier: Programming Language :: Python :: 3
Classifier: License :: OSI Approved :: MIT License
Classifier: Operating System :: OS Independent
Requires-Python: >=3.5
Requires-Dist: Bio (>=0.1.0)
Requires-Dist: biopandas (>=0.2.5)
Requires-Dist: matplotlib (>=3.1.1)
Requires-Dist: numpy (>=1.17.2)
Requires-Dist: pandas (>=0.25.1)
Requires-Dist: plotly (>=4.7.0)
Requires-Dist: scikit-learn (==0.23.2)
Requires-Dist: scipy (>=1.3.1)
Requires-Dist: seaborn (>=0.9.0)
